Metadata-Version: 2.1
Name: cpat-audit
Version: 1.4.1
Summary: Collector de auditoria para CPATs
Author: Arkhotech Spa
Author-email: msilval@arkho.io
Classifier: Programming Language :: Python :: 3
Classifier: License :: OSI Approved :: MIT License
Classifier: Operating System :: OS Independent
Requires-Python: >=3.6
